routeros_api/__init__.py
routeros_api/api.py
routeros_api/api_socket.py
routeros_api/api_structure.py
routeros_api/base_api.py
routeros_api/communication_exception_parsers.py
routeros_api/exceptions.py
routeros_api/query.py
routeros_api/resource.py
routeros_api/sentence.py
routeros_api/utils.py
routeros_api/api_communicator/__init__.py
routeros_api/api_communicator/async_decorator.py
routeros_api/api_communicator/base.py
routeros_api/api_communicator/encoding_decorator.py
routeros_api/api_communicator/exception_decorator.py
routeros_api/api_communicator/key_cleaner_decorator.py
tests/__init__.py
tests/test_api_communicator.py
tests/test_base_api.py
tests/test_login_router_os_api.py
tests/test_resource.py
tests/test_sentence.py
tests/test_socket.py
RouterOS_7_api-0.18.1.dev0.dist-info/LICENSE
RouterOS_7_api-0.18.1.dev0.dist-info/METADATA
RouterOS_7_api-0.18.1.dev0.dist-info/WHEEL
RouterOS_7_api-0.18.1.dev0.dist-info/top_level.txt
RouterOS_7_api-0.18.1.dev0.dist-info/RECORD
