Metadata-Version: 2.1
Name: RouterOS-7-api
Version: 0.18.1.dev0
Summary: Python API to RouterBoard devices produced by MikroTik.
Home-page: https://github.com/Andollini89/RouterOS-api
Author: Social WiFi
Author-email: it@socialwifi.com
License: MIT
Platform: UNKNOWN
Classifier: Development Status :: 5 - Production/Stable
Classifier: License :: OSI Approved :: MIT License
Classifier: Operating System :: OS Independent
Classifier: Programming Language :: Python
Classifier: Programming Language :: Python :: 2
Classifier: Programming Language :: Python :: 2.7
Classifier: Programming Language :: Python :: 3
Classifier: Programming Language :: Python :: 3.4
Classifier: Programming Language :: Python :: 3.5
Classifier: Programming Language :: Python :: 3.6
Classifier: Programming Language :: Python :: 3.7
License-File: LICENSE
Requires-Dist: six
